[
  {
    "line": 1,
    "elements": [
      {
        "before": [
          {
            "result": {
              "duration": 59507751300,
              "status": "passed"
            },
            "match": {
              "location": "Stepdefinition.beforeExecution()"
            }
          }
        ],
        "line": 10,
        "name": "login with Valid Username and invalid Password",
        "description": "",
        "id": "login-authentication-validation-of-facebook-appication;login-with-valid-username-and-invalid-password;;2",
        "after": [
          {
            "result": {
              "duration": 3654198500,
              "status": "passed"
            },
            "match": {
              "location": "Stepdefinition.afterexecution()"
            }
          }
        ],
        "type": "scenario",
        "keyword": "Scenario Outline",
        "steps": [
          {
            "result": {
              "duration": 15566864300,
              "status": "passed"
            },
            "line": 4,
            "name": "launch Facebook application",
            "match": {
              "location": "Stepdefinition.launch_Facebook_application()"
            },
            "keyword": "Given "
          },
          {
            "result": {
              "duration": 4865679700,
              "status": "passed"
            },
            "line": 5,
            "name": "Enter valid  \"thiyaga\" and invalid \"thiyaga@123\"",
            "match": {
              "arguments": [
                {
                  "val": "thiyaga",
                  "offset": 14
                },
                {
                  "val": "thiyaga@123",
                  "offset": 36
                }
              ],
              "location": "Stepdefinition.enter_valid_and_invalid(String,String)"
            },
            "keyword": "When "
          },
          {
            "result": {
              "duration": 3901029200,
              "status": "passed"
            },
            "line": 6,
            "name": "Click login button",
            "match": {
              "location": "Stepdefinition.click_login_button()"
            },
            "keyword": "When "
          }
        ]
      },
      {
        "before": [
          {
            "result": {
              "duration": 16260853300,
              "status": "passed"
            },
            "match": {
              "location": "Stepdefinition.beforeExecution()"
            }
          }
        ],
        "line": 11,
        "name": "login with Valid Username and invalid Password",
        "description": "",
        "id": "login-authentication-validation-of-facebook-appication;login-with-valid-username-and-invalid-password;;3",
        "after": [
          {
            "result": {
              "duration": 852796700,
              "status": "passed"
            },
            "match": {
              "location": "Stepdefinition.afterexecution()"
            }
          }
        ],
        "type": "scenario",
        "keyword": "Scenario Outline",
        "steps": [
          {
            "result": {
              "duration": 31106572200,
              "status": "passed"
            },
            "line": 4,
            "name": "launch Facebook application",
            "match": {
              "location": "Stepdefinition.launch_Facebook_application()"
            },
            "keyword": "Given "
          },
          {
            "result": {
              "duration": 8847864200,
              "status": "passed"
            },
            "line": 5,
            "name": "Enter valid  \"ravi\" and invalid \"ravi@123\"",
            "match": {
              "arguments": [
                {
                  "val": "ravi",
                  "offset": 14
                },
                {
                  "val": "ravi@123",
                  "offset": 33
                }
              ],
              "location": "Stepdefinition.enter_valid_and_invalid(String,String)"
            },
            "keyword": "When "
          },
          {
            "result": {
              "duration": 5573044500,
              "status": "passed"
            },
            "line": 6,
            "name": "Click login button",
            "match": {
              "location": "Stepdefinition.click_login_button()"
            },
            "keyword": "When "
          }
        ]
      }
    ],
    "name": "login authentication validation of Facebook appication",
    "description": "",
    "id": "login-authentication-validation-of-facebook-appication",
    "keyword": "Feature",
    "uri": "C:/Users/mypc/eclipse-workspaces/FinalFb/src/test/resources/FeatureFiles/FinalFb.feature",
    "tags": []
  }
]